constellation/__about__.py
constellation/__init__.py
constellation/acme.py
constellation/config.py
constellation/constellation.py
constellation/docker_util.py
constellation/notifier.py
constellation/util.py
constellation/vault.py
constellation-1.5.0.dist-info/METADATA
constellation-1.5.0.dist-info/WHEEL
constellation-1.5.0.dist-info/RECORD
