Metadata-Version: 2.4
Name: constellation
Version: 1.5.0
Summary: Deploy scripts for constellations of docker containers
Project-URL: Documentation, https://github.com/reside-ic/constellation#readme
Project-URL: Issues, https://github.com/reside-ic/constellation/issues
Project-URL: Source, https://github.com/reside-ic/constellation
Author-email: Rich FitzJohn <r.fitzjohn@imperial.ac.uk>
License-Expression: MIT
Classifier: Development Status :: 4 - Beta
Classifier: Programming Language :: Python
Classifier: Programming Language :: Python :: 3.8
Classifier: Programming Language :: Python :: 3.9
Classifier: Programming Language :: Python :: 3.10
Classifier: Programming Language :: Python :: 3.11
Classifier: Programming Language :: Python :: 3.12
Classifier: Programming Language :: Python :: Implementation :: CPython
Classifier: Programming Language :: Python :: Implementation :: PyPy
Requires-Python: >=3.8
Requires-Dist: docker
Requires-Dist: hvac
Requires-Dist: pyyaml
Requires-Dist: requests
Requires-Dist: vault-dev
